catprep/__init__.py
catprep-0.0.4.dist-info/DESCRIPTION.rst
catprep-0.0.4.dist-info/METADATA
catprep-0.0.4.dist-info/RECORD
catprep-0.0.4.dist-info/WHEEL
catprep-0.0.4.dist-info/metadata.json
catprep-0.0.4.dist-info/top_level.txt
