Metadata-Version: 2.0
Name: catprep
Version: 0.0.4
Summary: A preprocessing library for categorical variables
Home-page: https://github.com/nel215/catprep
Author: nel215
Author-email: otomo.yuhei@gmail.com
License: UNKNOWN
Keywords: machine learning,preprocessing
Platform: UNKNOWN
Classifier: Development Status :: 3 - Alpha
Classifier: Environment :: Console
Classifier: License :: OSI Approved :: Apache Software License
Classifier: Topic :: Scientific/Engineering :: Artificial Intelligence
Requires-Dist: pandas
Requires-Dist: scikit-learn
